ptlearn/__init__.py
ptlearn/__main__.py
ptlearn/decorators/singleton.py
ptlearn/demo/ansible_runner/01_基础概念.py
ptlearn/demo/ansible_runner/02_执行Playbook.py
ptlearn/demo/ansible_runner/03_异步执行.py
ptlearn/demo/ansible_runner/04_事件处理.py
ptlearn/demo/ansible_runner/05_辅助函数.py
ptlearn/demo/ansible_runner/06_目录结构与配置.py
ptlearn/demo/ansible_runner/07_实战案例.py
ptlearn/demo/fabric/01_基础概念.py
ptlearn/demo/fabric/02_文件传输.py
ptlearn/demo/fabric/03_高级执行.py
ptlearn/demo/fabric/04_多主机操作.py
ptlearn/demo/fabric/05_实战部署.py
ptlearn/demo/fabric/06_fabfile与任务.py
ptlearn/demo/fabric/07_自定义任务加载.py
ptlearn/demo/fabric/08_Context类详解.py
ptlearn/demo/fabric/09_Task装饰器原理.py
ptlearn/demo/fabric/10_Task装饰器使用.py
ptlearn/demo/gitpython/01_基础操作.py
ptlearn/demo/gitpython/02_分支操作.py
ptlearn/demo/gitpython/03_提交与暂存.py
ptlearn/demo/gitpython/04_远程操作.py
ptlearn/demo/gitpython/05_文件与差异.py
ptlearn/demo/gitpython/06_高级功能.py
ptlearn/demo/gitpython/07_分支追踪与比较.py
ptlearn/demo/gradio/.gradio/flagged/dataset1.csv
ptlearn/demo/gradio/.gradio/flagged/dataset2.csv
ptlearn/demo/gradio/01_基础概念.py
ptlearn/demo/gradio/02_常用组件.py
ptlearn/demo/gradio/03_布局与样式.py
ptlearn/demo/gradio/04_事件与交互.py
ptlearn/demo/gradio/05_高级应用.py
ptlearn/demo/invoke/01_基础概念.py
ptlearn/demo/invoke/02_任务参数.py
ptlearn/demo/invoke/03_命令执行.py
ptlearn/demo/invoke/04_任务组织.py
ptlearn/demo/invoke/05_配置管理.py
ptlearn/demo/invoke/06_实战应用.py
ptlearn/demo/invoke/07_YAML配置文件.py
ptlearn/demo/jinja2/01_基础语法.py
ptlearn/demo/jinja2/02_控制结构.py
ptlearn/demo/jinja2/03_过滤器.py
ptlearn/demo/jinja2/04_模板继承.py
ptlearn/demo/jinja2/05_宏和包含.py
ptlearn/demo/jinja2/06_高级特性.py
ptlearn/demo/jinja2/07_实战应用.py
ptlearn/demo/lambda_expression/01_基础概念.py
ptlearn/demo/lambda_expression/02_常见应用场景.py
ptlearn/demo/lambda_expression/03_进阶技巧.py
ptlearn/demo/lambda_expression/04_实战案例.py
ptlearn/demo/lambda_expression/05_限制与最佳实践.py
ptlearn/demo/pathlib/01_基础概念.py
ptlearn/demo/pathlib/02_文件操作.py
ptlearn/demo/pathlib/03_目录遍历.py
ptlearn/demo/pathlib/04_路径模式与匹配.py
ptlearn-0.2.11.dist-info/WHEEL
ptlearn-0.2.11.dist-info/entry_points.txt
ptlearn-0.2.11.dist-info/METADATA
ptlearn-0.2.11.dist-info/RECORD
