Metadata-Version: 2.3
Name: ptlearn
Version: 0.2.11
Summary: Add your description here
Author: lipanpan
Author-email: lipanpan <lipanpanmail@163.com>
Requires-Dist: ansible-core>=2.20.1
Requires-Dist: ansible-runner>=2.4.2
Requires-Dist: celery>=5.6.1
Requires-Dist: fabric>=3.2.2
Requires-Dist: fire>=0.7.1
Requires-Dist: gitpython>=3.1.45
Requires-Dist: gradio>=6.3.0
Requires-Dist: jinja2>=3.1.6
Requires-Dist: prompt-toolkit>=3.0.52
Requires-Dist: pyperclip>=1.11.0
Requires-Dist: redis>=7.1.0
Requires-Dist: rich>=14.2.0
Requires-Dist: textual>=7.1.0
Requires-Dist: toml>=0.10.2
Requires-Dist: typer>=0.21.1
Requires-Python: ~=3.13.0
